ptp/__init__.py
ptp/ptp.py
ptp/libptp/__init__.py
ptp/libptp/constants.py
ptp/libptp/exceptions.py
ptp/libptp/parser.py
ptp/tools/__init__.py
ptp/tools/arachni/__init__.py
ptp/tools/arachni/parser.py
ptp/tools/burpsuite/__init__.py
ptp/tools/burpsuite/parser.py
ptp/tools/dirbuster/__init__.py
ptp/tools/dirbuster/parser.py
ptp/tools/dirbuster/signatures.py
ptp/tools/hoppy/__init__.py
ptp/tools/hoppy/parser.py
ptp/tools/metasploit/__init__.py
ptp/tools/metasploit/parser.py
ptp/tools/metasploit/signatures.py
ptp/tools/nmap/__init__.py
ptp/tools/nmap/parser.py
ptp/tools/nmap/signatures.py
ptp/tools/owasp/__init__.py
ptp/tools/owasp/cm008/__init__.py
ptp/tools/owasp/cm008/parser.py
ptp/tools/owasp/cm008/signatures.py
ptp/tools/robots/__init__.py
ptp/tools/robots/parser.py
ptp/tools/robots/signatures.py
ptp/tools/skipfish/__init__.py
ptp/tools/skipfish/parser.py
ptp/tools/w3af/__init__.py
ptp/tools/w3af/parser.py
ptp/tools/wapiti/__init__.py
ptp/tools/wapiti/parser.py
ptp/tools/wapiti/signatures.py
tests/__init__.py
tests/test_ptp.py
tests/utils.py
tests/libptp/__init__.py
tests/libptp/test_constants.py
tests/libptp/test_parser.py
tests/tools/__init__.py
tests/tools/arachni/__init__.py
tests/tools/arachni/arachni_json_reports_1_2_1.py
tests/tools/arachni/arachni_reports_1_0.py
tests/tools/arachni/arachni_reports_1_0_1.py
tests/tools/arachni/arachni_reports_1_0_2.py
tests/tools/arachni/arachni_reports_1_0_3.py
tests/tools/arachni/arachni_reports_1_0_4.py
tests/tools/arachni/arachni_reports_1_0_5.py
tests/tools/arachni/arachni_reports_1_0_6.py
tests/tools/arachni/arachni_reports_1_1.py
tests/tools/arachni/arachni_reports_1_2_1.py
tests/tools/arachni/test_parser.py
tests/tools/burpsuite/__init__.py
tests/tools/burpsuite/burp_1_6_30_report.py
tests/tools/burpsuite/test_parser.py
tests/tools/dirbuster/__init__.py
tests/tools/dirbuster/dirbuster_reports.py
tests/tools/dirbuster/test_parser.py
tests/tools/owasp/__init__.py
tests/tools/owasp/owasp_cm008_reports.py
owtf_ptp-0.4.3.dist-info/LICENSE
owtf_ptp-0.4.3.dist-info/METADATA
owtf_ptp-0.4.3.dist-info/WHEEL
owtf_ptp-0.4.3.dist-info/top_level.txt
owtf_ptp-0.4.3.dist-info/RECORD
