Metadata-Version: 2.1
Name: owtf-ptp
Version: 0.4.3
Summary: PTP parses and ranks the discoveries listed in security tool reports.
Home-page: https://owtf.github.io/ptp
Author: Tao Sauvage
Author-email: sauvage.tao@gmail.com
License: BSD
Keywords: PTP Security Automated Ranking
License-File: LICENSE
Requires-Dist: lxml
Requires-Dist: js2py
